setup.py
taxmagick/__init__.py
taxmagick/lineages.py
taxmagick/tree.py
taxmagick.egg-info/PKG-INFO
taxmagick.egg-info/SOURCES.txt
taxmagick.egg-info/dependency_links.txt
taxmagick.egg-info/entry_points.txt
taxmagick.egg-info/top_level.txt