Metadata-Version: 1.1
Name: taxmagick
Version: 0.1
Summary: Tools for managing ncbi taxonomic data
Home-page: https://github.com/crosenth/taxmagick
Author: Chris Rosenthal
Author-email: crosenth@gmail.com
License: GPLv3
Keywords: ncbi,rrndb,genetics,genomics
Platform: UNKNOWN
Classifier: License :: OSI Approved :: GNU General Public License v3 (GPLv3)
Classifier: Development Status :: 4 - Beta
Classifier: Environment :: Console
Classifier: Operating System :: OS Independent
Classifier: Intended Audience :: End Users/Desktop
Classifier: License :: OSI Approved :: GNU General Public License v3 (GPLv3)
Classifier: Programming Language :: Python :: 3 :: Only
